sopel_asn/__init__.py
sopel_asn/plugin.py
sopel_asn/util.py
sopel_asn-0.2.0.dist-info/licenses/COPYING
sopel_asn-0.2.0.dist-info/METADATA
sopel_asn-0.2.0.dist-info/WHEEL
sopel_asn-0.2.0.dist-info/entry_points.txt
sopel_asn-0.2.0.dist-info/top_level.txt
sopel_asn-0.2.0.dist-info/RECORD
