Metadata-Version: 2.4
Name: sopel-asn
Version: 0.2.0
Summary: ASN (and MAC address) lookup plugin for Sopel IRC bots
Author-email: dgw <dgw@technobabbl.es>
License-Expression: EFL-2.0
Project-URL: Homepage, https://github.com/dgw/sopel-asn
Project-URL: Bug Tracker, https://github.com/dgw/sopel-asn/issues
Keywords: sopel,plugin,bot,irc
Platform: Linux x86, x86-64
Classifier: Intended Audience :: Developers
Classifier: Intended Audience :: System Administrators
Classifier: Topic :: Communications :: Chat :: Internet Relay Chat
Requires-Python: <4,>=3.8
License-File: COPYING
Requires-Dist: sopel>=8.0
Dynamic: license-file
